pyasn1_fasder-0.1.3.dist-info/METADATA
pyasn1_fasder-0.1.3.dist-info/WHEEL
pyasn1_fasder-0.1.3.dist-info/licenses/LICENSE
pyasn1_fasder/error.py
pyasn1_fasder/_native_helper.py
pyasn1_fasder/__init__.py
pyasn1_fasder/_native.abi3.so
pyasn1_fasder-0.1.3.dist-info/RECORD
