Metadata-Version: 2.3
Name: pyasn1-fasder
Version: 0.1.3
Classifier: License :: OSI Approved :: MIT License
Classifier: Programming Language :: Rust
Classifier: Programming Language :: Python :: Implementation :: CPython
Classifier: Programming Language :: Python :: Implementation :: PyPy
Classifier: Programming Language :: Python :: 3
Classifier: Programming Language :: Python :: 3 :: Only
Classifier: Programming Language :: Python :: 3.9
Classifier: Programming Language :: Python :: 3.10
Classifier: Programming Language :: Python :: 3.11
Classifier: Programming Language :: Python :: 3.12
Classifier: Programming Language :: Python :: 3.13
Requires-Dist: pyasn1
License-File: LICENSE
Summary: A DER decoder for pyasn1 built to detect encoding errors
Author-email: Corey Bonnell <cbonnell@outlook.com>
License: MIT
Requires-Python: >=3.9
